flowdapt_sdk/__init__.py
flowdapt_sdk/_compat.py
flowdapt_sdk/api/__init__.py
flowdapt_sdk/api/base.py
flowdapt_sdk/api/configs.py
flowdapt_sdk/api/metrics.py
flowdapt_sdk/api/plugins.py
flowdapt_sdk/api/system.py
flowdapt_sdk/api/triggers.py
flowdapt_sdk/api/workflows.py
flowdapt_sdk/client.py
flowdapt_sdk/constants.py
flowdapt_sdk/dto/__init__.py
flowdapt_sdk/dto/base.py
flowdapt_sdk/dto/configs.py
flowdapt_sdk/dto/error.py
flowdapt_sdk/dto/metrics.py
flowdapt_sdk/dto/plugin.py
flowdapt_sdk/dto/resource.py
flowdapt_sdk/dto/system.py
flowdapt_sdk/dto/triggers.py
flowdapt_sdk/dto/workflows.py
flowdapt_sdk/errors.py
flowdapt_sdk/sdk.py
flowdapt_sdk/serialize.py
flowdapt_sdk/utils.py
flowdapt_sdk/version.py
flowdapt_sdk-0.1.8.dist-info/LICENSE
flowdapt_sdk-0.1.8.dist-info/METADATA
flowdapt_sdk-0.1.8.dist-info/WHEEL
flowdapt_sdk-0.1.8.dist-info/RECORD
