Metadata-Version: 2.3
Name: flowdapt_sdk
Version: 0.1.8
Summary: Python SDK for Flowdapt
License: MIT
Author: Emergent Methods
Author-email: contact@emergentmethods.ai
Requires-Python: >=3.10,<4.0
Classifier: License :: OSI Approved :: MIT License
Classifier: Programming Language :: Python :: 3
Classifier: Programming Language :: Python :: 3.10
Classifier: Programming Language :: Python :: 3.11
Classifier: Programming Language :: Python :: 3.12
Classifier: Programming Language :: Python :: 3.13
Requires-Dist: httpx (>=0.27.2,<1)
Requires-Dist: orjson (>=3.10.18,<4.0.0)
Requires-Dist: pydantic (>=2.11.4)
Project-URL: Repository, https://gitlab.com/emergentmethods/flowdapt-python-sdk
